pytest_notimplemented.py
pytest_notimplemented-1.0.0.dist-info/entry_points.txt
pytest_notimplemented-1.0.0.dist-info/LICENSE.md
pytest_notimplemented-1.0.0.dist-info/WHEEL
pytest_notimplemented-1.0.0.dist-info/METADATA
pytest_notimplemented-1.0.0.dist-info/RECORD
