Metadata-Version: 2.1
Name: pytest-notimplemented
Version: 1.0.0
Summary: Pytest markers for not implemented features and tests.
Home-page: https://github.com/neimad/pytest-notimplemented
License: GPL-3.0-or-later
Keywords: pytest,plugin,marker,skip,implemented
Author: Damien Flament
Author-email: damien.flament@gmx.com
Requires-Python: >=3.7,<4.0
Classifier: Framework :: Pytest
Classifier: Intended Audience :: Developers
Classifier: License :: OSI Approved :: GNU General Public License v3 or later (GPLv3+)
Classifier: Operating System :: OS Independent
Classifier: Programming Language :: Python :: 3
Classifier: Programming Language :: Python :: 3.7
Classifier: Topic :: Software Development :: Testing
Requires-Dist: pytest (>=5.1,<6.0)
Project-URL: Repository, https://github.com/neimad/pytest-notimplemented
